langgraph_cua-0.0.1.dist-info/METADATA
langgraph_cua-0.0.1.dist-info/WHEEL
langgraph_cua-0.0.1.dist-info/entry_points.txt
langgraph_cua-0.0.1.dist-info/licenses/LICENSE
langgraph_cua/__init__.py
langgraph_cua/graph.py
langgraph_cua/nodes/__init__.py
langgraph_cua/nodes/call_model.py
langgraph_cua/nodes/create_vm_instance.py
langgraph_cua/nodes/take_computer_action.py
langgraph_cua/types.py
langgraph_cua/utils.py
langgraph_cua-0.0.1.dist-info/RECORD
