Metadata-Version: 2.1
Name: langgraph-cua
Version: 0.0.1
Summary: An implementation of a computer use agent (CUA) using LangGraph
Author-Email: Brace Sproul <46789226+bracesproul@users.noreply.github.com>
Requires-Python: >=3.10
Requires-Dist: langgraph<0.4.0,>=0.3.17
Requires-Dist: langchain-core<0.4.0,>=0.3.46
Requires-Dist: scrapybara<3.0.0,>=2.4.1
Requires-Dist: langchain-openai<0.4.0,>=0.3.10
